{
  "$schema": "https://json-schema.org/draft/2020-12/schema",
  "$id": "https://raw.githubusercontent.com/api-evangelist/amazon-codeguru-profiler/refs/heads/main/json-schema/amazon-codeguru-profiler-profile-time-schema.json",
  "title": "ProfileTime",
  "description": " Contains the start time of a profile. ",
  "type": "object",
  "properties": {
    "start": {
      "allOf": [
        {
          "$ref": "#/components/schemas/Timestamp"
        },
        {
          "description": "The start time of a profile. It is specified using the ISO 8601 format. For example, 2020-06-01T13:15:02.001Z represents 1 millisecond past June 1, 2020 1:15:02 PM UTC."
        }
      ]
    }
  }
}